tksidebar/__init__.py
tksidebar/sidebar.py
tksidebar-0.2.4.dist-info/LICENSE
tksidebar-0.2.4.dist-info/METADATA
tksidebar-0.2.4.dist-info/WHEEL
tksidebar-0.2.4.dist-info/top_level.txt
tksidebar-0.2.4.dist-info/RECORD
