Metadata-Version: 2.1
Name: tksidebar
Version: 0.2.4
Summary: a nice sidebar for tkinter app GUI
Home-page: https://github.com/youssefhoummad/tk_sidebare
Author: youssef Hoummad
Author-email: youssefhoummad@outlook.com
License: UNKNOWN
Project-URL: Bug Tracker, https://github.com/youssefhoummad/tk_sidebare/issues
Platform: UNKNOWN
Classifier: Programming Language :: Python :: 3
Classifier: License :: OSI Approved :: MIT License
Classifier: Operating System :: OS Independent
Requires-Python: >=3.6
License-File: LICENSE
